adafruit_circuitpython_usb_host_mouse-1.5.1.dist-info/licenses/LICENSE
adafruit_usb_host_mouse/__init__.py
adafruit_usb_host_mouse/mouse_cursor.bmp
adafruit_usb_host_mouse/mouse_cursor.bmp.license
adafruit_circuitpython_usb_host_mouse-1.5.1.dist-info/METADATA
adafruit_circuitpython_usb_host_mouse-1.5.1.dist-info/WHEEL
adafruit_circuitpython_usb_host_mouse-1.5.1.dist-info/top_level.txt
adafruit_circuitpython_usb_host_mouse-1.5.1.dist-info/RECORD
