Metadata-Version: 2.4
Name: adafruit-circuitpython-usb-host-mouse
Version: 1.5.1
Summary: Helper class that encapsulates the objects needed for user code to interact with a USB mouse, draw a visible cursor, and determine when buttons are pressed.
Author-email: Adafruit Industries <circuitpython@adafruit.com>
License: MIT
Project-URL: Homepage, https://github.com/adafruit/Adafruit_CircuitPython_USB_Host_Mouse
Keywords: adafruit,blinka,circuitpython,micropython,usb_host_mouse,usb,mouse,mice,usbhost,usbmouse,usbmice,host,cursor
Classifier: Intended Audience :: Developers
Classifier: Topic :: Software Development :: Libraries
Classifier: Topic :: Software Development :: Embedded Systems
Classifier: Topic :: System :: Hardware
Classifier: License :: OSI Approved :: MIT License
Classifier: Programming Language :: Python :: 3
License-File: LICENSE
Requires-Dist: Adafruit-Blinka
Requires-Dist: adafruit-circuitpython-usb-host-descriptors
Provides-Extra: optional
Dynamic: license-file
